house_sales/__init__.py
house_sales/config/__init__.py
house_sales/config/core.py
house_sales/config.yml
house_sales/datasets/__init__.py
house_sales/datasets/test.csv
house_sales/pipeline.py
house_sales/predict.py
house_sales/processing/__init__.py
house_sales/processing/data_manager.py
house_sales/processing/features.py
house_sales/processing/validation.py
house_sales/train_pipeline.py
house_sales/trained_models/__init__.py
house_sales/trained_models/regression_model_output_v0.0.4.pkl
house_sales-0.0.4.dist-info/entry_points.txt
house_sales-0.0.4.dist-info/LICENSE
house_sales-0.0.4.dist-info/WHEEL
house_sales-0.0.4.dist-info/METADATA
house_sales-0.0.4.dist-info/RECORD
