Metadata-Version: 2.1
Name: house-sales
Version: 0.0.4
Summary: House Sales
Home-page: https://github.com/paulrousset/house-sales
License: MIT
Author: Paul Rousset
Author-email: paulrousset@hotmail.fr
Requires-Python: >=3.8,<4.0
Classifier: Development Status :: 5 - Production/Stable
Classifier: License :: OSI Approved :: MIT License
Classifier: Programming Language :: Python :: 3
Classifier: Programming Language :: Python :: 3.8
Classifier: Programming Language :: Python :: 3.9
Classifier: Programming Language :: Python :: 3.10
Classifier: Programming Language :: Python :: 3.11
Requires-Dist: click (>=8.0.1)
Requires-Dist: feature-engine (>=1.5.1,<2.0.0)
Requires-Dist: joblib (>=1.2.0,<2.0.0)
Requires-Dist: nox (>=2022.8.7,<2023.0.0)
Requires-Dist: numpy (>=1.23.4,<2.0.0)
Requires-Dist: pandas (>=1.5.1,<2.0.0)
Requires-Dist: pre-commit (>=2.20.0,<3.0.0)
Requires-Dist: pydantic (>=1.10.2,<2.0.0)
Requires-Dist: scikit-learn (>=1.1.3,<2.0.0)
Requires-Dist: scipy (>=1.8.1,<2.0.0)
Requires-Dist: strictyaml (>=1.6.2,<2.0.0)
Project-URL: Changelog, https://github.com/paulrousset/house-sales/releases
Project-URL: Documentation, https://house-sales.readthedocs.io
Project-URL: Repository, https://github.com/paulrousset/house-sales
